OxVoxNNS-0.1.0.dist-info/METADATA
OxVoxNNS-0.1.0.dist-info/WHEEL
OxVoxNNS-0.1.0.dist-info/license_files/LICENSE
ox_vox_nns/__init__.py
ox_vox_nns/ox_vox_nns.cpython-38-x86_64-linux-gnu.so
OxVoxNNS-0.1.0.dist-info/RECORD
